openmdao/__init__.py
openmdao/api.py
openmdao/components/__init__.py
openmdao/components/constraint.py
openmdao/components/exec_comp.py
openmdao/components/external_code.py
openmdao/components/indep_var_comp.py
openmdao/components/linear_system.py
openmdao/components/meta_model.py
openmdao/components/multifi_meta_model.py
openmdao/components/param_comp.py
openmdao/components/subproblem.py
openmdao/components/unit_comp.py
openmdao/components/test/__init__.py
openmdao/components/test/external_code_for_testing.py
openmdao/components/test/test_exec_comp.py
openmdao/components/test/test_external_code.py
openmdao/components/test/test_indep_var_comp.py
openmdao/components/test/test_linear_system.py
openmdao/components/test/test_meta_model.py
openmdao/components/test/test_multifi_meta_model.py
openmdao/components/test/test_unit_comp.py
openmdao/core/__init__.py
openmdao/core/_checks.py
openmdao/core/basic_impl.py
openmdao/core/component.py
openmdao/core/data_transfer.py
openmdao/core/driver.py
openmdao/core/fileref.py
openmdao/core/group.py
openmdao/core/mpi_wrap.py
openmdao/core/parallel_fd_group.py
openmdao/core/parallel_group.py
openmdao/core/petsc_impl.py
openmdao/core/problem.py
openmdao/core/relevance.py
openmdao/core/system.py
openmdao/core/vec_wrapper.py
openmdao/core/vec_wrapper_complex_step.py
openmdao/core/test/__init__.py
openmdao/core/test/test_calc_gradient.py
openmdao/core/test/test_check_derivatives.py
openmdao/core/test/test_comp_complex_step.py
openmdao/core/test/test_comp_fd_jacobian.py
openmdao/core/test/test_complex_step.py
openmdao/core/test/test_component.py
openmdao/core/test/test_component_derivatives.py
openmdao/core/test/test_connections.py
openmdao/core/test/test_driver_interface.py
openmdao/core/test/test_empty_jacobian.py
openmdao/core/test/test_fileref.py
openmdao/core/test/test_group.py
openmdao/core/test/test_group_derivatives.py
openmdao/core/test/test_layout.py
openmdao/core/test/test_parallel_group.py
mms_openmdao-1.7.5.dist-info/LICENSE.txt
mms_openmdao-1.7.5.dist-info/METADATA
mms_openmdao-1.7.5.dist-info/WHEEL
mms_openmdao-1.7.5.dist-info/entry_points.txt
mms_openmdao-1.7.5.dist-info/top_level.txt
mms_openmdao-1.7.5.dist-info/RECORD
