Metadata-Version: 2.1
Name: mms-openmdao
Version: 1.7.5
Summary: OpenMDAO v1 framework infrastructure
Home-page: http://openmdao.org
Download-URL: https://pypi.python.org/pypi/mms-openmdao/
Author: OpenMDAO Team
Author-email: openmdao@openmdao.org
License: Apache License, Version 2.0
Keywords: optimization multidisciplinary multi-disciplinary analysis
Classifier: Development Status :: 3 - Alpha
Classifier: Intended Audience :: Science/Research
Classifier: License :: OSI Approved :: Apache Software License
Classifier: Natural Language :: English
Classifier: Operating System :: MacOS :: MacOS X
Classifier: Operating System :: POSIX :: Linux
Classifier: Operating System :: Microsoft :: Windows
Classifier: Topic :: Scientific/Engineering
Classifier: Programming Language :: Python
Classifier: Programming Language :: Python :: 2.7
Classifier: Programming Language :: Python :: 3.4
Classifier: Programming Language :: Python :: Implementation :: CPython
License-File: LICENSE.txt
Requires-Dist: six
Requires-Dist: numpydoc
Requires-Dist: numpy >=1.20
Requires-Dist: scipy
Requires-Dist: sqlitedict
Requires-Dist: pyparsing
Requires-Dist: decorator
